vecna/__init__.py
vecna/config.py
vecna/main.py
vecna/models.py
vecna/commands/__init__.py
vecna/commands/generate.py
vecna/commands/init.py
vecna/commands/lock.py
vecna/commands/unlock.py
vecna/commands/version.py
vecna/commands/alias/__init__.py
vecna/commands/alias/add.py
vecna/commands/alias/delete.py
vecna/commands/alias/get.py
vecna/commands/alias/list.py
vecna/commands/alias/update.py
vecna/commands/creds/__init__.py
vecna/commands/creds/add.py
vecna/commands/creds/delete.py
vecna/commands/creds/get.py
vecna/commands/creds/list.py
vecna/commands/creds/update.py
vecna/core/__init__.py
vecna/core/session.py
vecna/core/vault.py
vecna/utils/__init__.py
vecna/utils/clipboard.py
vecna/utils/password_generator.py
vecna/utils/secure_file.py
vecna-0.1.2.dist-info/licenses/LICENCE
vecna-0.1.2.dist-info/METADATA
vecna-0.1.2.dist-info/WHEEL
vecna-0.1.2.dist-info/entry_points.txt
vecna-0.1.2.dist-info/top_level.txt
vecna-0.1.2.dist-info/RECORD
