Metadata-Version: 2.4
Name: vecna
Version: 0.1.2
Summary: Vault for Encrypted Credentials, Notes, and Aliases
Author-email: Thomas Rapai <th.rapai@hotmail.com>
License-Expression: MIT
Requires-Python: >=3.10
License-File: LICENCE
Requires-Dist: typer
Requires-Dist: cryptography
Requires-Dist: pyperclip
Provides-Extra: dev
Requires-Dist: pytest; extra == "dev"
Requires-Dist: pytest-cov; extra == "dev"
Requires-Dist: pre-commit; extra == "dev"
Dynamic: license-file
